aaron/__init__.py
aaron/_modidx.py
aaron/datasets.py
aaron/defaults.py
aaron/mpl.py
aaron/openai.py
aaron/utils.py
aaron/web.py
aaron/ai/__init__.py
aaron/ai/accel.py
aaron/ai/activations.py
aaron/ai/augment.py
aaron/ai/conv.py
aaron/ai/datasets.py
aaron/ai/fid.py
aaron/ai/init.py
aaron/ai/learner.py
aaron/ai/resnet.py
aaron/ai/sgd.py
aaron/ai/training.py
aaron-0.0.2.dist-info/LICENSE
aaron-0.0.2.dist-info/METADATA
aaron-0.0.2.dist-info/WHEEL
aaron-0.0.2.dist-info/entry_points.txt
aaron-0.0.2.dist-info/top_level.txt
aaron-0.0.2.dist-info/RECORD
