Metadata-Version: 2.1
Name: aaron
Version: 0.0.2
Summary: A python library of convenience
Home-page: https://github.com/aaronsgithub/aaron
Author: Aaron
Author-email: sendaaronstuff@outlook.com
License: Apache Software License 2.0
Keywords: nbdev jupyter notebook python
Classifier: Development Status :: 4 - Beta
Classifier: Intended Audience :: Developers
Classifier: Natural Language :: English
Classifier: Programming Language :: Python :: 3.10
Classifier: License :: OSI Approved :: Apache Software License
Requires-Python: >=3.10
License-File: LICENSE
Requires-Dist: fastcore
Requires-Dist: pandas
Requires-Dist: torch
Requires-Dist: numpy
Requires-Dist: matplotlib
Requires-Dist: scikit-learn
Requires-Dist: tiktoken
Requires-Dist: beautifulsoup4
Requires-Dist: playwright
Requires-Dist: httpx
Requires-Dist: requests
Requires-Dist: rich
Requires-Dist: datasets
Requires-Dist: torchvision
Requires-Dist: torcheval
Requires-Dist: accelerate
Requires-Dist: fastprogress
Requires-Dist: lxml
Requires-Dist: html5lib
Provides-Extra: dev
